qscout/v1/std/jaqal_action.py
qscout/v1/std/jaqal_gates.py
qscout/v1/std/noisy.py
qscout/v1/std/stretched/jaqal_action.py
qscout/v1/std/stretched/jaqal_gates.py
qscout/v1/zz/jaqal_action.py
qscout/v1/zz/jaqal_gates.py
qscout_gatemodels-1.3.0.data/data/share/qscout-gatemodels/tests/__init__.py
qscout_gatemodels-1.3.0.data/data/share/qscout-gatemodels/tests/parser/__init__.py
qscout_gatemodels-1.3.0.data/data/share/qscout-gatemodels/tests/parser/test_jaqalpup_parser.py
qscout_gatemodels-1.3.0.dist-info/licenses/LICENSE
qscout_gatemodels-1.3.0.dist-info/licenses/NOTICE
qscout_gatemodels-1.3.0.dist-info/METADATA
qscout_gatemodels-1.3.0.dist-info/WHEEL
qscout_gatemodels-1.3.0.dist-info/top_level.txt
qscout_gatemodels-1.3.0.dist-info/RECORD
