Metadata-Version: 2.4
Name: QSCOUT-gatemodels
Version: 1.3.0
Summary: QSCOUT Gate Models
Home-page: https://qscout.sandia.gov
Author: Benjamin C. A. Morrison, Jay Wesley Van Der Wall, Daniel Lobser, Antonio Russo, Kenneth Rudinger, Peter Maunz
Author-email: qscout@sandia.gov
License: Apache
Classifier: Development Status :: 4 - Beta
Classifier: Intended Audience :: Science/Research
Classifier: License :: OSI Approved :: Apache Software License
Classifier: Programming Language :: Python :: 3
Classifier: Topic :: Scientific/Engineering :: Physics
Classifier: Operating System :: Microsoft :: Windows
Classifier: Operating System :: MacOS :: MacOS X
Classifier: Operating System :: Unix
Requires-Python: >=3.6.5
License-File: LICENSE
License-File: NOTICE
Requires-Dist: JaqalPaq>=1.3.0
Requires-Dist: numpy
Provides-Extra: tests
Requires-Dist: pytest; extra == "tests"
Dynamic: license-file
